{
    "image": "ha-dev:x86_64-pc-ubuntu-gcc-x11",
    "remoteUser": "hadev"
    // ,
    // "containerEnv": {
    //     "DISPLAY": "${localEnv:DISPLAY}",
    //     "WAYLAND_DISPLAY": "${localEnv:WAYLAND_DISPLAY}",
    //     "XDG_RUNTIME_DIR": "${localEnv:XDG_RUNTIME_DIR}",
    //     "PULSE_SERVER": "${localEnv:PULSE_SERVER}"
    // },
    // "mounts": [
    //     {
    //         "source": "/tmp/.X11-unix",
    //         "target": "/tmp/.X11-unix",
    //         "type": "volume"
    //     },
    //     {
    //         "source": "/mnt/wslg",
    //         "target": "/mnt/wslg",
    //         "type": "volume"
    //     }
    // ]
}